LICENSE.txt
MANIFEST.in
README.md
pyproject.toml
setup.cfg
setup.py
PyAsyncDNS/__init__.py
PyAsyncDNS/__main__.py
PyAsyncDNS/client.py
PyAsyncDNS/exfiltrator.py
PyAsyncDNS/exfiltrator_server.py
PyAsyncDNS/lib.py
PyAsyncDNS/server.py
PyAsyncDNS.egg-info/PKG-INFO
PyAsyncDNS.egg-info/SOURCES.txt
PyAsyncDNS.egg-info/dependency_links.txt
PyAsyncDNS.egg-info/entry_points.txt
PyAsyncDNS.egg-info/top_level.txt